.hgignore
LICENSE.txt
MANIFEST.in
README
VERSION
contributors.txt
requirements.txt
setup.cfg
setup.py
docs/Makefile
docs/conf.py
docs/index.rst
docs/make.bat
docs/plugin_devs/arguments.rst
docs/plugin_devs/dev_commands.rst
docs/plugin_devs/dev_plugins.rst
docs/plugin_devs/first_steps.rst
docs/protocols/index.rst
nekbot/__init__.py
nekbot.egg-info/PKG-INFO
nekbot.egg-info/SOURCES.txt
nekbot.egg-info/dependency_links.txt
nekbot.egg-info/not-zip-safe
nekbot.egg-info/top_level.txt
nekbot/conf/__init__.py
nekbot/conf/global_settings.py
nekbot/conf/locale/es/LC_MESSAGES/nekbot.po
nekbot/conf/plugin_template/LICENSE.txt
nekbot/conf/plugin_template/MANIFEST.in
nekbot/conf/plugin_template/README
nekbot/conf/plugin_template/VERSION
nekbot/conf/plugin_template/contributors.txt
nekbot/conf/plugin_template/requirements.txt
nekbot/conf/plugin_template/setup.cfg
nekbot/conf/plugin_template/setup.py
nekbot/conf/plugin_template/nekbot/__init__.py
nekbot/conf/plugin_template/nekbot/plugins/__init__.py
nekbot/conf/plugin_template/nekbot/plugins/plugin_template/__init__.py
nekbot/conf/project_template/nekbot
nekbot/conf/project_template/settings.py
nekbot/conf/project_template/plugins/__init__.py
nekbot/conf/project_template/storage/.hgkeep
nekbot/core/__init__.py
nekbot/core/exceptions.py
nekbot/core/handlers.py
nekbot/core/management.py
nekbot/core/modular.py
nekbot/core/signals.py
nekbot/core/commands/__init__.py
nekbot/core/commands/argparse.py
nekbot/core/commands/control.py
nekbot/core/commands/doc.py
nekbot/core/commands/temp.py
nekbot/core/permissions/__init__.py
nekbot/core/types/__init__.py
nekbot/core/types/argparse.py
nekbot/core/types/filesystem.py
nekbot/plugins/__init__.py
nekbot/plugins/bot.py
nekbot/plugins/commands.py
nekbot/plugins/hello.py
nekbot/plugins/test.py
nekbot/protocols/__init__.py
nekbot/protocols/base/__init__.py
nekbot/protocols/base/event.py
nekbot/protocols/base/group_chat.py
nekbot/protocols/base/message.py
nekbot/protocols/base/send.py
nekbot/protocols/base/user.py
nekbot/storage/__init__.py
nekbot/storage/ejdb.py
nekbot/storage/meuh.py
nekbot/utils/__init__.py
nekbot/utils/auth.py
